langchain_redis/__init__.py
langchain_redis/cache.py
langchain_redis/chat_message_history.py
langchain_redis/config.py
langchain_redis/py.typed
langchain_redis/vectorstores.py
langchain_redis/version.py
langchain_redis-0.2.4.dist-info/LICENSE
langchain_redis-0.2.4.dist-info/METADATA
langchain_redis-0.2.4.dist-info/WHEEL
langchain_redis-0.2.4.dist-info/RECORD
