Metadata-Version: 2.1
Name: langchain-redis
Version: 0.2.4
Summary: An integration package connecting Redis and LangChain for AI working memory
Home-page: https://github.com/langchain-ai/langchain-redis
License: MIT
Author: Brian Sam-Bodden
Author-email: bsb@redis.com
Requires-Python: >=3.9,<3.14
Classifier: License :: OSI Approved :: MIT License
Classifier: Programming Language :: Python :: 3
Classifier: Programming Language :: Python :: 3.9
Classifier: Programming Language :: Python :: 3.10
Classifier: Programming Language :: Python :: 3.11
Classifier: Programming Language :: Python :: 3.12
Requires-Dist: anyio (>=4.9.0,<5.0.0)
Requires-Dist: certifi (>=2025.4.26,<2026.0.0)
Requires-Dist: httpcore (>=1.0.9,<2.0.0)
Requires-Dist: jinja2 (>=3.1.6,<4.0.0)
Requires-Dist: langchain-core (>=0.3,<0.4)
Requires-Dist: python-ulid (>=3.0.0)
Requires-Dist: redisvl (>=0.6.0,<1.0.0)
Requires-Dist: typing-extensions (>=4.13.2,<5.0.0)
Requires-Dist: urllib3 (>=2.4.0,<3.0.0)
Project-URL: Repository, https://github.com/langchain-ai/langchain-redis
Project-URL: Source Code, https://github.com/langchain-ai/langchain-redis/tree/main/libs/redis
